{
  "v": "5.7.5",
  "fr": 80,
  "ip": 0,
  "op": 160,
  "w": 1200,
  "h": 1200,
  "nm": "Comp 1",
  "ddd": 0,
  "assets": [],
  "layers": [
    {
      "ddd": 0,
      "ind": 0,
      "ty": 3,
      "nm": "",
      "sr": 1,
      "ks": {
        "o": { "a": 0, "k": 100, "ix": 2 },
        "r": { "a": 0, "k": 0, "ix": 2 },
        "p": { "a": 0, "k": [600.0000305175781, 599.9999694824219], "ix": 2 },
        "a": { "a": 0, "k": [0, 0], "ix": 2 },
        "s": { "a": 0, "k": [80, 80], "ix": 2 }
      },
      "ao": 0,
      "ip": 0,
      "op": 161,
      "st": 0,
      "bm": 0,
      "hd": false
    },
    {
      "ddd": 0,
      "ind": 1,
      "ty": 3,
      "nm": "",
      "sr": 1,
      "ks": {
        "o": { "a": 0, "k": 100, "ix": 2 },
        "r": {
          "a": 1,
          "k": [
            {
              "t": 0,
              "s": [-4.811735094603771],
              "i": { "x": [1], "y": [1] },
              "o": { "x": [0.42], "y": [0] }
            },
            {
              "t": 13,
              "s": [1.089256707054176e-7],
              "i": { "x": [1], "y": [1] },
              "o": { "x": [0.42], "y": [0] }
            },
            {
              "t": 26,
              "s": [-4.811735094603771],
              "i": { "x": [1], "y": [1] },
              "o": { "x": [0.42], "y": [0] }
            },
            {
              "t": 41,
              "s": [1.089256707054176e-7],
              "i": { "x": [1], "y": [1] },
              "o": { "x": [0.42], "y": [0] }
            },
            {
              "t": 54,
              "s": [-4.811735094603771],
              "i": { "x": [1], "y": [1] },
              "o": { "x": [0.42], "y": [0] }
            },
            {
              "t": 67,
              "s": [1.089256707054176e-7],
              "i": { "x": [1], "y": [1] },
              "o": { "x": [0.42], "y": [0] }
            },
            {
              "t": 80,
              "s": [-4.811735094603771],
              "i": { "x": [1], "y": [1] },
              "o": { "x": [0.42], "y": [0] }
            },
            {
              "t": 93,
              "s": [1.089256707054176e-7],
              "i": { "x": [1], "y": [1] },
              "o": { "x": [0.42], "y": [0] }
            },
            {
              "t": 107,
              "s": [-4.811735094603771],
              "i": { "x": [1], "y": [1] },
              "o": { "x": [0.42], "y": [0] }
            },
            {
              "t": 121,
              "s": [1.089256707054176e-7],
              "i": { "x": [1], "y": [1] },
              "o": { "x": [0.42], "y": [0] }
            },
            {
              "t": 134,
              "s": [-4.811735094603771],
              "i": { "x": [1], "y": [1] },
              "o": { "x": [0.42], "y": [0] }
            },
            {
              "t": 147,
              "s": [1.089256707054176e-7],
              "i": { "x": [1], "y": [1] },
              "o": { "x": [0.42], "y": [0] }
            },
            {
              "t": 160,
              "s": [-4.811735094603771],
              "i": { "x": [1], "y": [1] },
              "o": { "x": [0], "y": [0] }
            }
          ],
          "ix": 2
        },
        "p": {
          "a": 1,
          "k": [
            {
              "t": 0,
              "s": [-5.881159572962133, 5.608141086965475],
              "i": { "x": [1], "y": [1] },
              "o": { "x": [0.42], "y": [0] }
            },
            {
              "t": 13,
              "s": [-4.226511745813696, -43.3746164813939],
              "i": { "x": [1], "y": [1] },
              "o": { "x": [0.42], "y": [0] }
            },
            {
              "t": 26,
              "s": [-5.881159572962133, 5.608141086965475],
              "i": { "x": [1], "y": [1] },
              "o": { "x": [0.42], "y": [0] }
            },
            {
              "t": 41,
              "s": [-4.226511745813696, -43.3746164813939],
              "i": { "x": [1], "y": [1] },
              "o": { "x": [0.42], "y": [0] }
            },
            {
              "t": 54,
              "s": [-5.881159572962133, 5.608141086965475],
              "i": { "x": [1], "y": [1] },
              "o": { "x": [0.42], "y": [0] }
            },
            {
              "t": 67,
              "s": [-4.226511745813696, -43.3746164813939],
              "i": { "x": [1], "y": [1] },
              "o": { "x": [0.42], "y": [0] }
            },
            {
              "t": 80,
              "s": [-5.881159572962133, 5.608141086965475],
              "i": { "x": [1], "y": [1] },
              "o": { "x": [0.42], "y": [0] }
            },
            {
              "t": 93,
              "s": [-4.226511745813696, -43.3746164813939],
              "i": { "x": [1], "y": [1] },
              "o": { "x": [0.42], "y": [0] }
            },
            {
              "t": 107,
              "s": [-5.881159572962133, 5.608141086965475],
              "i": { "x": [1], "y": [1] },
              "o": { "x": [0.42], "y": [0] }
            },
            {
              "t": 121,
              "s": [-4.226511745813696, -43.3746164813939],
              "i": { "x": [1], "y": [1] },
              "o": { "x": [0.42], "y": [0] }
            },
            {
              "t": 134,
              "s": [-5.881159572962133, 5.608141086965475],
              "i": { "x": [1], "y": [1] },
              "o": { "x": [0.42], "y": [0] }
            },
            {
              "t": 147,
              "s": [-4.226511745813696, -43.3746164813939],
              "i": { "x": [1], "y": [1] },
              "o": { "x": [0.42], "y": [0] }
            },
            {
              "t": 160,
              "s": [-5.881159572962133, 5.608141086965475],
              "i": { "x": [1], "y": [1] },
              "o": { "x": [0], "y": [0] }
            }
          ],
          "ix": 2
        },
        "a": { "a": 0, "k": [0, 0], "ix": 2 },
        "s": { "a": 0, "k": [207.55135497749188, 207.55135497749203], "ix": 2 }
      },
      "ao": 0,
      "ip": 0,
      "op": 161,
      "st": 0,
      "bm": 0,
      "hd": false,
      "parent": 0
    },
    {
      "ddd": 0,
      "ind": 2,
      "ty": 4,
      "nm": "Leg",
      "sr": 1,
      "ks": {
        "o": { "a": 0, "k": 100, "ix": 2 },
        "r": { "a": 0, "k": 0, "ix": 2 },
        "p": { "a": 0, "k": [0, 0], "ix": 2 },
        "a": { "a": 0, "k": [0, 0], "ix": 2 },
        "s": { "a": 0, "k": [100, 100], "ix": 2 }
      },
      "ao": 0,
      "hd": false,
      "parent": 1,
      "shapes": [
        {
          "ty": "gr",
          "hd": false,
          "it": [
            {
              "ty": "sh",
              "hd": false,
              "d": 1,
              "ks": {
                "a": 1,
                "k": [
                  {
                    "t": 0,
                    "s": [
                      {
                        "c": false,
                        "v": [
                          [-35.4786376953125, -36.120361328125],
                          [30.63491821289062, -56.16635513305664],
                          [17.30557250976562, 13.68649101257324]
                        ],
                        "i": [
                          [0, 0],
                          [0, 0],
                          [0, 0]
                        ],
                        "o": [
                          [0, 0],
                          [0, 0],
                          [0, 0]
                        ]
                      }
                    ],
                    "i": { "x": [1], "y": [1] },
                    "o": { "x": [0.42], "y": [0] }
                  },
                  {
                    "t": 26,
                    "s": [
                      {
                        "c": false,
                        "v": [
                          [-35.4786376953125, -36.120361328125],
                          [-39.34900665283203, 34.94673538208008],
                          [-59.59439468383789, 100.0125961303711]
                        ],
                        "i": [
                          [0, 0],
                          [0, 0],
                          [0, 0]
                        ],
                        "o": [
                          [0, 0],
                          [0, 0],
                          [0, 0]
                        ]
                      }
                    ],
                    "i": { "x": [1], "y": [1] },
                    "o": { "x": [0.42], "y": [0] }
                  },
                  {
                    "t": 54,
                    "s": [
                      {
                        "c": false,
                        "v": [
                          [-35.4786376953125, -36.120361328125],
                          [30.63491821289062, -56.16635513305664],
                          [17.30557250976562, 13.68649101257324]
                        ],
                        "i": [
                          [0, 0],
                          [0, 0],
                          [0, 0]
                        ],
                        "o": [
                          [0, 0],
                          [0, 0],
                          [0, 0]
                        ]
                      }
                    ],
                    "i": { "x": [1], "y": [1] },
                    "o": { "x": [0.42], "y": [0] }
                  },
                  {
                    "t": 80,
                    "s": [
                      {
                        "c": false,
                        "v": [
                          [-35.4786376953125, -36.120361328125],
                          [-39.34900665283203, 34.94673538208008],
                          [-59.59439468383789, 100.0125961303711]
                        ],
                        "i": [
                          [0, 0],
                          [0, 0],
                          [0, 0]
                        ],
                        "o": [
                          [0, 0],
                          [0, 0],
                          [0, 0]
                        ]
                      }
                    ],
                    "i": { "x": [1], "y": [1] },
                    "o": { "x": [0.42], "y": [0] }
                  },
                  {
                    "t": 107,
                    "s": [
                      {
                        "c": false,
                        "v": [
                          [-35.4786376953125, -36.120361328125],
                          [30.63491821289062, -56.16635513305664],
                          [17.30557250976562, 13.68649101257324]
                        ],
                        "i": [
                          [0, 0],
                          [0, 0],
                          [0, 0]
                        ],
                        "o": [
                          [0, 0],
                          [0, 0],
                          [0, 0]
                        ]
                      }
                    ],
                    "i": { "x": [1], "y": [1] },
                    "o": { "x": [0.42], "y": [0] }
                  },
                  {
                    "t": 134,
                    "s": [
                      {
                        "c": false,
                        "v": [
                          [-35.4786376953125, -36.120361328125],
                          [-39.34900665283203, 34.94673538208008],
                          [-59.59439468383789, 100.0125961303711]
                        ],
                        "i": [
                          [0, 0],
                          [0, 0],
                          [0, 0]
                        ],
                        "o": [
                          [0, 0],
                          [0, 0],
                          [0, 0]
                        ]
                      }
                    ],
                    "i": { "x": [1], "y": [1] },
                    "o": { "x": [0.42], "y": [0] }
                  },
                  {
                    "t": 160,
                    "s": [
                      {
                        "c": false,
                        "v": [
                          [-35.4786376953125, -36.120361328125],
                          [30.63491821289062, -56.16635513305664],
                          [17.30557250976562, 13.68649101257324]
                        ],
                        "i": [
                          [0, 0],
                          [0, 0],
                          [0, 0]
                        ],
                        "o": [
                          [0, 0],
                          [0, 0],
                          [0, 0]
                        ]
                      }
                    ],
                    "i": { "x": [1], "y": [1] },
                    "o": { "x": [0], "y": [0] }
                  }
                ],
                "ix": 2
              }
            },
            {
              "ty": "st",
              "c": { "a": 0, "k": [0, 0, 0], "ix": 2 },
              "o": { "a": 0, "k": 100, "ix": 2 },
              "w": { "a": 0, "k": 28, "ix": 2 },
              "hd": false,
              "lc": 2,
              "lj": 2
            },
            {
              "ty": "tm",
              "s": { "a": 0, "k": 0, "ix": 2 },
              "e": { "a": 0, "k": 100, "ix": 2 },
              "o": { "a": 0, "k": 0, "ix": 2 },
              "m": 1,
              "hd": false
            },
            {
              "ty": "tr",
              "hd": false,
              "p": {
                "a": 0,
                "k": [19.77581787109375, 41.87823486328125],
                "ix": 2
              },
              "a": { "a": 0, "k": [0, 0], "ix": 2 },
              "s": { "a": 0, "k": [100, 100], "ix": 2 },
              "r": { "a": 0, "k": 0, "ix": 2 },
              "o": { "a": 0, "k": 100, "ix": 2 },
              "sk": { "a": 0, "k": 0, "ix": 2 },
              "sa": { "a": 0, "k": 0, "ix": 2 }
            }
          ]
        }
      ],
      "ip": 0,
      "op": 161,
      "st": 0,
      "bm": 0
    },
    {
      "ddd": 0,
      "ind": 3,
      "ty": 4,
      "nm": "Leg",
      "sr": 1,
      "ks": {
        "o": { "a": 0, "k": 100, "ix": 2 },
        "r": { "a": 0, "k": 0, "ix": 2 },
        "p": { "a": 0, "k": [0, 0], "ix": 2 },
        "a": { "a": 0, "k": [0, 0], "ix": 2 },
        "s": { "a": 0, "k": [100, 100], "ix": 2 }
      },
      "ao": 0,
      "hd": false,
      "parent": 1,
      "shapes": [
        {
          "ty": "gr",
          "hd": false,
          "it": [
            {
              "ty": "sh",
              "hd": false,
              "d": 1,
              "ks": {
                "a": 1,
                "k": [
                  {
                    "t": 0,
                    "s": [
                      {
                        "c": false,
                        "v": [
                          [-35.4786376953125, -34.624267578125],
                          [-41.20303344726562, 36.33258438110352],
                          [-63.303955078125, 97.43513488769531]
                        ],
                        "i": [
                          [0, 0],
                          [0, 0],
                          [0, 0]
                        ],
                        "o": [
                          [0, 0],
                          [0, 0],
                          [0, 0]
                        ]
                      }
                    ],
                    "i": { "x": [1], "y": [1] },
                    "o": { "x": [0.42], "y": [0] }
                  },
                  {
                    "t": 26,
                    "s": [
                      {
                        "c": false,
                        "v": [
                          [-35.4786376953125, -34.624267578125],
                          [27.3707103729248, -62.33753204345703],
                          [36.05666732788086, -13.46086502075195]
                        ],
                        "i": [
                          [0, 0],
                          [0, 0],
                          [0, 0]
                        ],
                        "o": [
                          [0, 0],
                          [0, 0],
                          [0, 0]
                        ]
                      }
                    ],
                    "i": { "x": [1], "y": [1] },
                    "o": { "x": [0.42], "y": [0] }
                  },
                  {
                    "t": 54,
                    "s": [
                      {
                        "c": false,
                        "v": [
                          [-35.4786376953125, -34.624267578125],
                          [-41.20303344726562, 36.33258438110352],
                          [-63.303955078125, 97.43513488769531]
                        ],
                        "i": [
                          [0, 0],
                          [0, 0],
                          [0, 0]
                        ],
                        "o": [
                          [0, 0],
                          [0, 0],
                          [0, 0]
                        ]
                      }
                    ],
                    "i": { "x": [1], "y": [1] },
                    "o": { "x": [0.42], "y": [0] }
                  },
                  {
                    "t": 80,
                    "s": [
                      {
                        "c": false,
                        "v": [
                          [-35.4786376953125, -34.624267578125],
                          [27.3707103729248, -62.33753204345703],
                          [36.05666732788086, -13.46086502075195]
                        ],
                        "i": [
                          [0, 0],
                          [0, 0],
                          [0, 0]
                        ],
                        "o": [
                          [0, 0],
                          [0, 0],
                          [0, 0]
                        ]
                      }
                    ],
                    "i": { "x": [1], "y": [1] },
                    "o": { "x": [0.42], "y": [0] }
                  },
                  {
                    "t": 107,
                    "s": [
                      {
                        "c": false,
                        "v": [
                          [-35.4786376953125, -34.624267578125],
                          [-41.20303344726562, 36.33258438110352],
                          [-63.303955078125, 97.43513488769531]
                        ],
                        "i": [
                          [0, 0],
                          [0, 0],
                          [0, 0]
                        ],
                        "o": [
                          [0, 0],
                          [0, 0],
                          [0, 0]
                        ]
                      }
                    ],
                    "i": { "x": [1], "y": [1] },
                    "o": { "x": [0.42], "y": [0] }
                  },
                  {
                    "t": 134,
                    "s": [
                      {
                        "c": false,
                        "v": [
                          [-35.4786376953125, -34.624267578125],
                          [27.3707103729248, -62.33753204345703],
                          [36.05666732788086, -13.46086502075195]
                        ],
                        "i": [
                          [0, 0],
                          [0, 0],
                          [0, 0]
                        ],
                        "o": [
                          [0, 0],
                          [0, 0],
                          [0, 0]
                        ]
                      }
                    ],
                    "i": { "x": [1], "y": [1] },
                    "o": { "x": [0.42], "y": [0] }
                  },
                  {
                    "t": 160,
                    "s": [
                      {
                        "c": false,
                        "v": [
                          [-35.4786376953125, -34.624267578125],
                          [-41.20303344726562, 36.33258438110352],
                          [-63.303955078125, 97.43513488769531]
                        ],
                        "i": [
                          [0, 0],
                          [0, 0],
                          [0, 0]
                        ],
                        "o": [
                          [0, 0],
                          [0, 0],
                          [0, 0]
                        ]
                      }
                    ],
                    "i": { "x": [1], "y": [1] },
                    "o": { "x": [0], "y": [0] }
                  }
                ],
                "ix": 2
              }
            },
            {
              "ty": "st",
              "c": { "a": 0, "k": [0, 0, 0], "ix": 2 },
              "o": { "a": 0, "k": 100, "ix": 2 },
              "w": { "a": 0, "k": 28, "ix": 2 },
              "hd": false,
              "lc": 2,
              "lj": 2
            },
            {
              "ty": "tm",
              "s": { "a": 0, "k": 0, "ix": 2 },
              "e": { "a": 0, "k": 100, "ix": 2 },
              "o": { "a": 0, "k": 0, "ix": 2 },
              "m": 1,
              "hd": false
            },
            {
              "ty": "tr",
              "hd": false,
              "p": {
                "a": 0,
                "k": [19.77581787109375, 41.87823486328125],
                "ix": 2
              },
              "a": { "a": 0, "k": [0, 0], "ix": 2 },
              "s": { "a": 0, "k": [100, 100], "ix": 2 },
              "r": { "a": 0, "k": 0, "ix": 2 },
              "o": { "a": 0, "k": 100, "ix": 2 },
              "sk": { "a": 0, "k": 0, "ix": 2 },
              "sa": { "a": 0, "k": 0, "ix": 2 }
            }
          ]
        }
      ],
      "ip": 0,
      "op": 161,
      "st": 0,
      "bm": 0
    },
    {
      "ddd": 0,
      "ind": 4,
      "ty": 4,
      "nm": "Arm",
      "sr": 1,
      "ks": {
        "o": { "a": 0, "k": 100, "ix": 2 },
        "r": { "a": 0, "k": 0, "ix": 2 },
        "p": { "a": 0, "k": [0, 0], "ix": 2 },
        "a": { "a": 0, "k": [0, 0], "ix": 2 },
        "s": { "a": 0, "k": [100, 100], "ix": 2 }
      },
      "ao": 0,
      "hd": false,
      "parent": 1,
      "shapes": [
        {
          "ty": "gr",
          "hd": false,
          "it": [
            {
              "ty": "sh",
              "hd": false,
              "d": 1,
              "ks": {
                "a": 1,
                "k": [
                  {
                    "t": 0,
                    "s": [
                      {
                        "c": false,
                        "v": [
                          [-7.468924522399902, -18.74538993835449],
                          [49.63563919067383, 8.534337043762207],
                          [80.18434143066406, -29.26351928710938]
                        ],
                        "i": [
                          [0, 0],
                          [0, 0],
                          [0, 0]
                        ],
                        "o": [
                          [0, 0],
                          [0, 0],
                          [0, 0]
                        ]
                      }
                    ],
                    "i": { "x": [1], "y": [1] },
                    "o": { "x": [0.42], "y": [0] }
                  },
                  {
                    "t": 26,
                    "s": [
                      {
                        "c": false,
                        "v": [
                          [16.63317489624023, 1.391406536102295],
                          [62.3103141784668, 17.60598945617676],
                          [88.45626831054688, -25.8134708404541]
                        ],
                        "i": [
                          [0, 0],
                          [0, 0],
                          [0, 0]
                        ],
                        "o": [
                          [0, 0],
                          [0, 0],
                          [0, 0]
                        ]
                      }
                    ],
                    "i": { "x": [1], "y": [1] },
                    "o": { "x": [0.42], "y": [0] }
                  },
                  {
                    "t": 54,
                    "s": [
                      {
                        "c": false,
                        "v": [
                          [-7.468924522399902, -18.74538993835449],
                          [49.63563919067383, 8.534337043762207],
                          [80.18434143066406, -29.26351928710938]
                        ],
                        "i": [
                          [0, 0],
                          [0, 0],
                          [0, 0]
                        ],
                        "o": [
                          [0, 0],
                          [0, 0],
                          [0, 0]
                        ]
                      }
                    ],
                    "i": { "x": [1], "y": [1] },
                    "o": { "x": [0.42], "y": [0] }
                  },
                  {
                    "t": 80,
                    "s": [
                      {
                        "c": false,
                        "v": [
                          [16.63317489624023, 1.391406536102295],
                          [62.3103141784668, 17.60598945617676],
                          [88.45626831054688, -25.8134708404541]
                        ],
                        "i": [
                          [0, 0],
                          [0, 0],
                          [0, 0]
                        ],
                        "o": [
                          [0, 0],
                          [0, 0],
                          [0, 0]
                        ]
                      }
                    ],
                    "i": { "x": [1], "y": [1] },
                    "o": { "x": [0.42], "y": [0] }
                  },
                  {
                    "t": 107,
                    "s": [
                      {
                        "c": false,
                        "v": [
                          [-7.468924522399902, -18.74538993835449],
                          [49.63563919067383, 8.534337043762207],
                          [80.18434143066406, -29.26351928710938]
                        ],
                        "i": [
                          [0, 0],
                          [0, 0],
                          [0, 0]
                        ],
                        "o": [
                          [0, 0],
                          [0, 0],
                          [0, 0]
                        ]
                      }
                    ],
                    "i": { "x": [1], "y": [1] },
                    "o": { "x": [0.42], "y": [0] }
                  },
                  {
                    "t": 134,
                    "s": [
                      {
                        "c": false,
                        "v": [
                          [16.63317489624023, 1.391406536102295],
                          [62.3103141784668, 17.60598945617676],
                          [88.45626831054688, -25.8134708404541]
                        ],
                        "i": [
                          [0, 0],
                          [0, 0],
                          [0, 0]
                        ],
                        "o": [
                          [0, 0],
                          [0, 0],
                          [0, 0]
                        ]
                      }
                    ],
                    "i": { "x": [1], "y": [1] },
                    "o": { "x": [0.42], "y": [0] }
                  },
                  {
                    "t": 160,
                    "s": [
                      {
                        "c": false,
                        "v": [
                          [-7.468924522399902, -18.74538993835449],
                          [49.63563919067383, 8.534337043762207],
                          [80.18434143066406, -29.26351928710938]
                        ],
                        "i": [
                          [0, 0],
                          [0, 0],
                          [0, 0]
                        ],
                        "o": [
                          [0, 0],
                          [0, 0],
                          [0, 0]
                        ]
                      }
                    ],
                    "i": { "x": [1], "y": [1] },
                    "o": { "x": [0], "y": [0] }
                  }
                ],
                "ix": 2
              }
            },
            {
              "ty": "st",
              "c": { "a": 0, "k": [0, 0, 0], "ix": 2 },
              "o": { "a": 0, "k": 100, "ix": 2 },
              "w": { "a": 0, "k": 28, "ix": 2 },
              "hd": false,
              "lc": 2,
              "lj": 2
            },
            {
              "ty": "tm",
              "s": { "a": 0, "k": 0, "ix": 2 },
              "e": { "a": 0, "k": 100, "ix": 2 },
              "o": { "a": 0, "k": 0, "ix": 2 },
              "m": 1,
              "hd": false
            },
            {
              "ty": "tr",
              "hd": false,
              "p": {
                "a": 1,
                "k": [
                  {
                    "t": 0,
                    "s": [2.342529296875, -69.666259765625],
                    "i": { "x": [1], "y": [1] },
                    "o": { "x": [0.42], "y": [0] }
                  },
                  {
                    "t": 26,
                    "s": [1.342529296875, -65.666259765625],
                    "i": { "x": [1], "y": [1] },
                    "o": { "x": [0.42], "y": [0] }
                  },
                  {
                    "t": 54,
                    "s": [2.342529296875, -69.666259765625],
                    "i": { "x": [1], "y": [1] },
                    "o": { "x": [0.42], "y": [0] }
                  },
                  {
                    "t": 80,
                    "s": [1.342529296875, -65.666259765625],
                    "i": { "x": [1], "y": [1] },
                    "o": { "x": [0.42], "y": [0] }
                  },
                  {
                    "t": 107,
                    "s": [2.342529296875, -69.666259765625],
                    "i": { "x": [1], "y": [1] },
                    "o": { "x": [0.42], "y": [0] }
                  },
                  {
                    "t": 134,
                    "s": [1.342529296875, -65.666259765625],
                    "i": { "x": [1], "y": [1] },
                    "o": { "x": [0.42], "y": [0] }
                  },
                  {
                    "t": 160,
                    "s": [2.342529296875, -69.666259765625],
                    "i": { "x": [1], "y": [1] },
                    "o": { "x": [0], "y": [0] }
                  }
                ],
                "ix": 2
              },
              "a": {
                "a": 0,
                "k": [1.61883544921875, -10.36459112167358],
                "ix": 2
              },
              "s": {
                "a": 0,
                "k": [99.99999865150161, 99.99999865150161],
                "ix": 2
              },
              "r": {
                "a": 1,
                "k": [
                  {
                    "t": 0,
                    "s": [-1.200558585878753e-7],
                    "i": { "x": [1], "y": [1] },
                    "o": { "x": [0.42], "y": [0] }
                  },
                  {
                    "t": 26,
                    "s": [164.9999998799441],
                    "i": { "x": [1], "y": [1] },
                    "o": { "x": [0.42], "y": [0] }
                  },
                  {
                    "t": 54,
                    "s": [-1.200558585878753e-7],
                    "i": { "x": [1], "y": [1] },
                    "o": { "x": [0.42], "y": [0] }
                  },
                  {
                    "t": 80,
                    "s": [164.9999998799441],
                    "i": { "x": [1], "y": [1] },
                    "o": { "x": [0.42], "y": [0] }
                  },
                  {
                    "t": 107,
                    "s": [-1.200558585878753e-7],
                    "i": { "x": [1], "y": [1] },
                    "o": { "x": [0.42], "y": [0] }
                  },
                  {
                    "t": 134,
                    "s": [164.9999998799441],
                    "i": { "x": [1], "y": [1] },
                    "o": { "x": [0.42], "y": [0] }
                  },
                  {
                    "t": 160,
                    "s": [-1.200558585878753e-7],
                    "i": { "x": [1], "y": [1] },
                    "o": { "x": [0], "y": [0] }
                  }
                ],
                "ix": 2
              },
              "o": { "a": 0, "k": 100, "ix": 2 },
              "sk": { "a": 0, "k": 0, "ix": 2 },
              "sa": { "a": 0, "k": 0, "ix": 2 }
            }
          ]
        }
      ],
      "ip": 0,
      "op": 161,
      "st": 0,
      "bm": 0
    },
    {
      "ddd": 0,
      "ind": 5,
      "ty": 4,
      "nm": "Arm",
      "sr": 1,
      "ks": {
        "o": { "a": 0, "k": 100, "ix": 2 },
        "r": { "a": 0, "k": 0, "ix": 2 },
        "p": { "a": 0, "k": [0, 0], "ix": 2 },
        "a": { "a": 0, "k": [0, 0], "ix": 2 },
        "s": { "a": 0, "k": [100, 100], "ix": 2 }
      },
      "ao": 0,
      "hd": false,
      "parent": 1,
      "shapes": [
        {
          "ty": "gr",
          "hd": false,
          "it": [
            {
              "ty": "sh",
              "hd": false,
              "d": 1,
              "ks": {
                "a": 1,
                "k": [
                  {
                    "t": 0,
                    "s": [
                      {
                        "c": false,
                        "v": [
                          [-81.4534683227539, 31.4677791595459],
                          [-70.61968231201172, -17.83401489257812],
                          [-15.92657470703125, -17.83401298522949]
                        ],
                        "i": [
                          [0, 0],
                          [0, 0],
                          [0, 0]
                        ],
                        "o": [
                          [0, 0],
                          [0, 0],
                          [0, 0]
                        ]
                      }
                    ],
                    "i": { "x": [1], "y": [1] },
                    "o": { "x": [0.42], "y": [0] }
                  },
                  {
                    "t": 26,
                    "s": [
                      {
                        "c": false,
                        "v": [
                          [-69.80569458007812, 50.75856018066406],
                          [-76.03254699707031, 5.892193794250488],
                          [-17.15262985229492, -16.811279296875]
                        ],
                        "i": [
                          [0, 0],
                          [0, 0],
                          [0, 0]
                        ],
                        "o": [
                          [0, 0],
                          [0, 0],
                          [0, 0]
                        ]
                      }
                    ],
                    "i": { "x": [1], "y": [1] },
                    "o": { "x": [0.42], "y": [0] }
                  },
                  {
                    "t": 54,
                    "s": [
                      {
                        "c": false,
                        "v": [
                          [-81.4534683227539, 31.4677791595459],
                          [-70.61968231201172, -17.83401489257812],
                          [-15.92657470703125, -17.83401298522949]
                        ],
                        "i": [
                          [0, 0],
                          [0, 0],
                          [0, 0]
                        ],
                        "o": [
                          [0, 0],
                          [0, 0],
                          [0, 0]
                        ]
                      }
                    ],
                    "i": { "x": [1], "y": [1] },
                    "o": { "x": [0.42], "y": [0] }
                  },
                  {
                    "t": 80,
                    "s": [
                      {
                        "c": false,
                        "v": [
                          [-69.80569458007812, 50.75856018066406],
                          [-76.03254699707031, 5.892193794250488],
                          [-17.15262985229492, -16.811279296875]
                        ],
                        "i": [
                          [0, 0],
                          [0, 0],
                          [0, 0]
                        ],
                        "o": [
                          [0, 0],
                          [0, 0],
                          [0, 0]
                        ]
                      }
                    ],
                    "i": { "x": [1], "y": [1] },
                    "o": { "x": [0.42], "y": [0] }
                  },
                  {
                    "t": 107,
                    "s": [
                      {
                        "c": false,
                        "v": [
                          [-81.4534683227539, 31.4677791595459],
                          [-70.61968231201172, -17.83401489257812],
                          [-15.92657470703125, -17.83401298522949]
                        ],
                        "i": [
                          [0, 0],
                          [0, 0],
                          [0, 0]
                        ],
                        "o": [
                          [0, 0],
                          [0, 0],
                          [0, 0]
                        ]
                      }
                    ],
                    "i": { "x": [1], "y": [1] },
                    "o": { "x": [0.42], "y": [0] }
                  },
                  {
                    "t": 134,
                    "s": [
                      {
                        "c": false,
                        "v": [
                          [-69.80569458007812, 50.75856018066406],
                          [-76.03254699707031, 5.892193794250488],
                          [-17.15262985229492, -16.811279296875]
                        ],
                        "i": [
                          [0, 0],
                          [0, 0],
                          [0, 0]
                        ],
                        "o": [
                          [0, 0],
                          [0, 0],
                          [0, 0]
                        ]
                      }
                    ],
                    "i": { "x": [1], "y": [1] },
                    "o": { "x": [0.42], "y": [0] }
                  },
                  {
                    "t": 160,
                    "s": [
                      {
                        "c": false,
                        "v": [
                          [-81.4534683227539, 31.4677791595459],
                          [-70.61968231201172, -17.83401489257812],
                          [-15.92657470703125, -17.83401298522949]
                        ],
                        "i": [
                          [0, 0],
                          [0, 0],
                          [0, 0]
                        ],
                        "o": [
                          [0, 0],
                          [0, 0],
                          [0, 0]
                        ]
                      }
                    ],
                    "i": { "x": [1], "y": [1] },
                    "o": { "x": [0], "y": [0] }
                  }
                ],
                "ix": 2
              }
            },
            {
              "ty": "st",
              "c": { "a": 0, "k": [0, 0, 0], "ix": 2 },
              "o": { "a": 0, "k": 100, "ix": 2 },
              "w": { "a": 0, "k": 28, "ix": 2 },
              "hd": false,
              "lc": 2,
              "lj": 2
            },
            {
              "ty": "tm",
              "s": { "a": 0, "k": 0, "ix": 2 },
              "e": { "a": 0, "k": 100, "ix": 2 },
              "o": { "a": 0, "k": 0, "ix": 2 },
              "m": 1,
              "hd": false
            },
            {
              "ty": "tr",
              "hd": false,
              "p": {
                "a": 1,
                "k": [
                  {
                    "t": 0,
                    "s": [-9.2806396484375, -78.04708862304688],
                    "i": { "x": [1], "y": [1] },
                    "o": { "x": [0.42], "y": [0] }
                  },
                  {
                    "t": 26,
                    "s": [-10.2806396484375, -74.047119140625],
                    "i": { "x": [1], "y": [1] },
                    "o": { "x": [0.42], "y": [0] }
                  },
                  {
                    "t": 54,
                    "s": [-9.2806396484375, -78.04708862304688],
                    "i": { "x": [1], "y": [1] },
                    "o": { "x": [0.42], "y": [0] }
                  },
                  {
                    "t": 80,
                    "s": [-10.2806396484375, -74.047119140625],
                    "i": { "x": [1], "y": [1] },
                    "o": { "x": [0.42], "y": [0] }
                  },
                  {
                    "t": 107,
                    "s": [-9.2806396484375, -78.04708862304688],
                    "i": { "x": [1], "y": [1] },
                    "o": { "x": [0.42], "y": [0] }
                  },
                  {
                    "t": 134,
                    "s": [-10.2806396484375, -74.047119140625],
                    "i": { "x": [1], "y": [1] },
                    "o": { "x": [0.42], "y": [0] }
                  },
                  {
                    "t": 160,
                    "s": [-9.2806396484375, -78.04708862304688],
                    "i": { "x": [1], "y": [1] },
                    "o": { "x": [0], "y": [0] }
                  }
                ],
                "ix": 2
              },
              "a": {
                "a": 0,
                "k": [-15.92657470703125, -17.83401489257812],
                "ix": 2
              },
              "s": {
                "a": 0,
                "k": [99.9999982885729, 99.99999828857288],
                "ix": 2
              },
              "r": {
                "a": 1,
                "k": [
                  {
                    "t": 0,
                    "s": [0],
                    "i": { "x": [1], "y": [1] },
                    "o": { "x": [0.42], "y": [0] }
                  },
                  {
                    "t": 26,
                    "s": [-135],
                    "i": { "x": [1], "y": [1] },
                    "o": { "x": [0.42], "y": [0] }
                  },
                  {
                    "t": 54,
                    "s": [0],
                    "i": { "x": [1], "y": [1] },
                    "o": { "x": [0.42], "y": [0] }
                  },
                  {
                    "t": 80,
                    "s": [-135],
                    "i": { "x": [1], "y": [1] },
                    "o": { "x": [0.42], "y": [0] }
                  },
                  {
                    "t": 107,
                    "s": [0],
                    "i": { "x": [1], "y": [1] },
                    "o": { "x": [0.42], "y": [0] }
                  },
                  {
                    "t": 134,
                    "s": [-135],
                    "i": { "x": [1], "y": [1] },
                    "o": { "x": [0.42], "y": [0] }
                  },
                  {
                    "t": 160,
                    "s": [0],
                    "i": { "x": [1], "y": [1] },
                    "o": { "x": [0], "y": [0] }
                  }
                ],
                "ix": 2
              },
              "o": { "a": 0, "k": 100, "ix": 2 },
              "sk": { "a": 0, "k": 0, "ix": 2 },
              "sa": { "a": 0, "k": 0, "ix": 2 }
            }
          ]
        }
      ],
      "ip": 0,
      "op": 161,
      "st": 0,
      "bm": 0
    },
    {
      "ddd": 0,
      "ind": 6,
      "ty": 4,
      "nm": "Body",
      "sr": 1,
      "ks": {
        "o": { "a": 0, "k": 100, "ix": 2 },
        "r": { "a": 0, "k": 0, "ix": 2 },
        "p": { "a": 0, "k": [0, 0], "ix": 2 },
        "a": { "a": 0, "k": [0, 0], "ix": 2 },
        "s": { "a": 0, "k": [100, 100], "ix": 2 }
      },
      "ao": 0,
      "hd": false,
      "parent": 1,
      "shapes": [
        {
          "ty": "gr",
          "hd": false,
          "it": [
            {
              "ty": "rc",
              "hd": false,
              "d": 1,
              "s": {
                "a": 1,
                "k": [
                  {
                    "t": 0,
                    "s": [49.42288121642103, 110.6426594346138],
                    "i": { "x": [1], "y": [1] },
                    "o": { "x": [0.42], "y": [0] }
                  },
                  {
                    "t": 26,
                    "s": [49.42288121642103, 109.2762551166799],
                    "i": { "x": [1], "y": [1] },
                    "o": { "x": [0.42], "y": [0] }
                  },
                  {
                    "t": 54,
                    "s": [49.42288121642103, 110.6426594346138],
                    "i": { "x": [1], "y": [1] },
                    "o": { "x": [0.42], "y": [0] }
                  },
                  {
                    "t": 80,
                    "s": [49.42288121642103, 109.2762551166799],
                    "i": { "x": [1], "y": [1] },
                    "o": { "x": [0.42], "y": [0] }
                  },
                  {
                    "t": 107,
                    "s": [49.42288121642103, 110.6426594346138],
                    "i": { "x": [1], "y": [1] },
                    "o": { "x": [0.42], "y": [0] }
                  },
                  {
                    "t": 134,
                    "s": [49.42288121642103, 109.2762551166799],
                    "i": { "x": [1], "y": [1] },
                    "o": { "x": [0.42], "y": [0] }
                  },
                  {
                    "t": 160,
                    "s": [49.42288121642103, 110.6426594346138],
                    "i": { "x": [1], "y": [1] },
                    "o": { "x": [0], "y": [0] }
                  }
                ],
                "ix": 2
              },
              "p": { "a": 0, "k": [0, 0], "ix": 2 },
              "r": { "a": 0, "k": 24.71144060821052, "ix": 2 }
            },
            {
              "ty": "fl",
              "c": { "a": 0, "k": [0, 0, 0], "ix": 2 },
              "o": { "a": 0, "k": 100, "ix": 2 },
              "r": 1,
              "bm": 0,
              "nm": "Fill 1",
              "mn": "ADBE Vector Graphic - Fill",
              "hd": false
            },
            {
              "ty": "tm",
              "s": { "a": 0, "k": 0, "ix": 2 },
              "e": { "a": 0, "k": 100, "ix": 2 },
              "o": { "a": 0, "k": 0, "ix": 2 },
              "m": 1,
              "hd": false
            },
            {
              "ty": "tr",
              "hd": false,
              "p": {
                "a": 1,
                "k": [
                  {
                    "t": 0,
                    "s": [-13.80194091796875, -36.84805297851562],
                    "i": { "x": [1], "y": [1] },
                    "o": { "x": [0.42], "y": [0] }
                  },
                  {
                    "t": 26,
                    "s": [-14.55133056640625, -34.41259765625],
                    "i": { "x": [1], "y": [1] },
                    "o": { "x": [0.42], "y": [0] }
                  },
                  {
                    "t": 54,
                    "s": [-13.80194091796875, -36.84805297851562],
                    "i": { "x": [1], "y": [1] },
                    "o": { "x": [0.42], "y": [0] }
                  },
                  {
                    "t": 80,
                    "s": [-14.55133056640625, -34.41259765625],
                    "i": { "x": [1], "y": [1] },
                    "o": { "x": [0.42], "y": [0] }
                  },
                  {
                    "t": 107,
                    "s": [-13.80194091796875, -36.84805297851562],
                    "i": { "x": [1], "y": [1] },
                    "o": { "x": [0.42], "y": [0] }
                  },
                  {
                    "t": 134,
                    "s": [-14.55133056640625, -34.41259765625],
                    "i": { "x": [1], "y": [1] },
                    "o": { "x": [0.42], "y": [0] }
                  },
                  {
                    "t": 160,
                    "s": [-13.80194091796875, -36.84805297851562],
                    "i": { "x": [1], "y": [1] },
                    "o": { "x": [0], "y": [0] }
                  }
                ],
                "ix": 2
              },
              "a": { "a": 0, "k": [0, 0], "ix": 2 },
              "s": {
                "a": 0,
                "k": [99.99999817013253, 99.99999817013254],
                "ix": 2
              },
              "r": { "a": 0, "k": 9.106247169633306, "ix": 2 },
              "o": { "a": 0, "k": 100, "ix": 2 },
              "sk": { "a": 0, "k": 0, "ix": 2 },
              "sa": { "a": 0, "k": 0, "ix": 2 }
            }
          ]
        }
      ],
      "ip": 0,
      "op": 161,
      "st": 0,
      "bm": 0
    },
    {
      "ddd": 0,
      "ind": 7,
      "ty": 4,
      "nm": "Head",
      "sr": 1,
      "ks": {
        "o": { "a": 0, "k": 100, "ix": 2 },
        "r": { "a": 0, "k": 0, "ix": 2 },
        "p": { "a": 0, "k": [0, 0], "ix": 2 },
        "a": { "a": 0, "k": [0, 0], "ix": 2 },
        "s": { "a": 0, "k": [100, 100], "ix": 2 }
      },
      "ao": 0,
      "hd": false,
      "parent": 1,
      "shapes": [
        {
          "ty": "gr",
          "hd": false,
          "it": [
            {
              "ty": "el",
              "hd": false,
              "d": 1,
              "s": {
                "a": 0,
                "k": [48.96759842626202, 48.96759842626202],
                "ix": 2
              },
              "p": { "a": 0, "k": [0, 0], "ix": 2 }
            },
            {
              "ty": "fl",
              "c": { "a": 0, "k": [0, 0, 0], "ix": 2 },
              "o": { "a": 0, "k": 100, "ix": 2 },
              "r": 1,
              "bm": 0,
              "nm": "Fill 1",
              "mn": "ADBE Vector Graphic - Fill",
              "hd": false
            },
            {
              "ty": "tm",
              "s": { "a": 0, "k": 0, "ix": 2 },
              "e": { "a": 0, "k": 100, "ix": 2 },
              "o": { "a": 0, "k": 0, "ix": 2 },
              "m": 1,
              "hd": false
            },
            {
              "ty": "tr",
              "hd": false,
              "p": {
                "a": 1,
                "k": [
                  {
                    "t": 0,
                    "s": [5.2379150390625, -119.7392272949219],
                    "i": { "x": [1], "y": [1] },
                    "o": { "x": [0.42], "y": [0] }
                  },
                  {
                    "t": 26,
                    "s": [-1.480423927307129, -122.5126419067383],
                    "i": { "x": [1], "y": [1] },
                    "o": { "x": [0.42], "y": [0] }
                  },
                  {
                    "t": 54,
                    "s": [5.2379150390625, -119.7392272949219],
                    "i": { "x": [1], "y": [1] },
                    "o": { "x": [0.42], "y": [0] }
                  },
                  {
                    "t": 80,
                    "s": [-1.480423927307129, -122.5126419067383],
                    "i": { "x": [1], "y": [1] },
                    "o": { "x": [0], "y": [0] }
                  },
                  {
                    "t": 107,
                    "s": [5.2379150390625, -119.7392272949219],
                    "i": { "x": [1], "y": [1] },
                    "o": { "x": [0.42], "y": [0] }
                  },
                  {
                    "t": 134,
                    "s": [-1.480423927307129, -122.5126419067383],
                    "i": { "x": [1], "y": [1] },
                    "o": { "x": [0], "y": [0] }
                  },
                  {
                    "t": 160,
                    "s": [5.2379150390625, -119.7392272949219],
                    "i": { "x": [1], "y": [1] },
                    "o": { "x": [0], "y": [0] }
                  }
                ],
                "ix": 2
              },
              "a": { "a": 0, "k": [0, 0], "ix": 2 },
              "s": { "a": 0, "k": [100, 100], "ix": 2 },
              "r": { "a": 0, "k": 0, "ix": 2 },
              "o": { "a": 0, "k": 100, "ix": 2 },
              "sk": { "a": 0, "k": 0, "ix": 2 },
              "sa": { "a": 0, "k": 0, "ix": 2 }
            }
          ]
        }
      ],
      "ip": 0,
      "op": 161,
      "st": 0,
      "bm": 0
    },
    {
      "ddd": 0,
      "ind": 8,
      "ty": 4,
      "nm": "Background",
      "sr": 1,
      "ks": {
        "o": { "a": 0, "k": 100, "ix": 2 },
        "r": { "a": 0, "k": 0, "ix": 2 },
        "p": { "a": 0, "k": [0, 0], "ix": 2 },
        "a": { "a": 0, "k": [0, 0], "ix": 2 },
        "s": { "a": 0, "k": [100, 100], "ix": 2 }
      },
      "ao": 0,
      "hd": false,
      "parent": 0,
      "shapes": [
        {
          "ty": "gr",
          "hd": false,
          "it": [
            {
              "ty": "rc",
              "hd": false,
              "d": 1,
              "s": {
                "a": 0,
                "k": [1199.999948457007, 1200.000032241971],
                "ix": 2
              },
              "p": { "a": 0, "k": [0, 0], "ix": 2 },
              "r": { "a": 0, "k": 599.9999742285036, "ix": 2 }
            },
            {
              "ty": "fl",
              "c": { "a": 0, "k": [1, 1, 1], "ix": 2 },
              "o": { "a": 0, "k": 99.99841209349594, "ix": 2 },
              "r": 1,
              "bm": 0,
              "nm": "Fill 1",
              "mn": "ADBE Vector Graphic - Fill",
              "hd": false
            },
            {
              "ty": "tm",
              "s": { "a": 0, "k": 0, "ix": 2 },
              "e": { "a": 0, "k": 100, "ix": 2 },
              "o": { "a": 0, "k": 0, "ix": 2 },
              "m": 1,
              "hd": false
            },
            {
              "ty": "tr",
              "hd": false,
              "p": {
                "a": 0,
                "k": [0.00006103515625, -0.00006103515625],
                "ix": 2
              },
              "a": { "a": 0, "k": [0, 0], "ix": 2 },
              "s": { "a": 0, "k": [100, 100], "ix": 2 },
              "r": { "a": 0, "k": 0, "ix": 2 },
              "o": { "a": 0, "k": 100, "ix": 2 },
              "sk": { "a": 0, "k": 0, "ix": 2 },
              "sa": { "a": 0, "k": 0, "ix": 2 }
            }
          ]
        }
      ],
      "ip": 0,
      "op": 161,
      "st": 0,
      "bm": 0
    }
  ],
  "markers": []
}
